{
  "originUrl": "https://www.virginvoyages.com",
  "aborted": false,
  "urls": [
    {
      "url": "https://www.virginvoyages.com/",
      "source": "MANUAL",
      "targetPath": "/",
      "id": "5f88c96fc63cc132332df0c7eb478084326c66bf"
    }
  ],
  "lastCrawled": "MANUAL",
  "crawlOptions": {
    "timeout": 10000,
    "inclusionPatterns": [],
    "exclusionPatterns": [],
    "limit": 100,
    "sameDomain": true,
    "keepHash": false,
    "strategy": "manual",
    "strategiesAttempted": [
      "MANUAL"
    ]
  },
  "extractionErrors": [],
  "errorCountMessage": "none"
}